{"topic": "List of physics concepts in primary and secondary education curricula", "english_title": "List of physics concepts in primary and secondary education curricula", "english": ["This", "list", "topics", "included", "high", "school", "physics", "curricula", "textbooks", "Mathematical", "Background", "SI", "Units", "Scalar", "physics", "Euclidean", "vector", "Motion", "graphs", "derivatives", "Pythagorean", "theorem", "Trigonometry", "Motion", "forces", "Motion", "Force", "Linear", "motion", "Linear", "motion", "Displacement", "Speed", "Velocity", "Acceleration", "Center", "mass", "Mass", "Momentum", "Newton", "laws", "motion", "Work", "physics", "Free", "body", "diagram", "Rotational", "motion", "Angular", "acceleration", "Angular", "momentum", "Introduction", "Angular", "velocity", "Centrifugal", "force", "Centripetal", "force", "Circular", "motion", "Tangential", "velocity", "Torque", "Conservation", "energy", "momentum", "Energy", "Conservation", "energy", "Elastic", "collision", "Inelastic", "collision", "Inertia", "Moment", "inertia", "Momentum", "Kinetic", "energy", "Potential", "energy", "Rotational", "energy", "Electricity", "magnetism", "Amp\u00e8re", "circuital", "law", "Capacitor", "Coulomb", "law", "Diode", "Direct", "current", "Electric", "charge", "Electric", "current", "Alternating", "current", "Electric", "field", "Electric", "potential", "energy", "Electron", "Faraday", "law", "induction", "Ion", "Inductor", "Joule", "heating", "Lenz", "law", "Magnetic", "field", "Ohm", "law", "Resistor", "Transistor", "Transformer", "Voltage", "Heat", "Entropy", "First", "law", "thermodynamics", "Heat", "Heat", "transfer", "Second", "law", "thermodynamics", "Temperature", "Thermal", "energy", "Thermodynamic", "cycle", "Volume", "thermodynamics", "Work", "thermodynamics", "Waves", "Wave", "Longitudinal", "wave", "Transverse", "waves", "Transverse", "wave", "Standing", "Waves", "Wavelength", "Frequency", "Light", "Light", "ray", "Speed", "light", "Sound", "Speed", "sound", "Radio", "waves", "Harmonic", "oscillator", "Hooke", "law", "Reflection", "Refraction", "Snell", "law", "Refractive", "index", "Total", "internal", "reflection", "Diffraction", "Interference", "wave", "propagation", "Polarization", "waves", "Vibrating", "string", "Doppler", "effect", "Gravity", "Gravitational", "potential", "Newton", "law", "universal", "gravitation", "Universal", "Gravitational", "Constant", "See", "also", "Outline", "physics", "Physics", "education", "References", "Further", "reading"], "chinese_title": "", "chinese": ""}