{"topic": "Hobby Hobby", "english_title": "Hobby Hobby", "english": ["Hobby", "Hobby", "song", "recorded", "German", "rapper", "Mero", "released", "18", "January", "2019", "Groove", "Attack", "TraX", "Written", "Enes", "Meral", "Mero", "produced", "Josh", "Petruccio", "track", "acts", "second", "single", "debut", "studio", "album", "Ya", "Hero", "Ya", "Mero", "2019", "An", "accompanying", "music", "video", "song", "directed", "Plug", "Jakub", "Tatjana", "100Blackdolphins", "uploaded", "onto", "Mero", "YouTube", "channel", "simultaneously", "single", "release", "Commercially", "single", "debuted", "atop", "German", "single", "charts", "broke", "multiple", "streaming", "records", "including", "streams", "Germany", "within", "one", "week", "accumalating", "nearly", "ten", "million", "streams", "Background", "composition", "Hobby", "Hobby", "announced", "Mero", "day", "prior", "release", "teaser", "social", "media", "services", "The", "track", "written", "produced", "Josh", "Petruccio", "previously", "produced", "Mero", "first", "single", "Baller", "los", "Music", "video", "The", "music", "video", "Hobby", "Hobby", "directed", "Plug", "Jakub", "Tatjana", "100Blackdolphins", "released", "18", "January", "2019", "The", "video", "viewed", "3", "1", "million", "times", "YouTube", "within", "first", "24", "hours", "breaking", "record", "Melodien", "Capital", "Bra", "Juju", "Commercial", "performance", "Hobby", "Hobby", "debut", "atop", "German", "singles", "chart", "issue", "dated", "25", "January", "2019", "second", "single", "The", "single", "also", "broke", "record", "streams", "one", "day", "one", "week", "Germany", "accumulating", "2", "1", "million", "nearly", "10", "million", "streams", "respectively", "Charts", "Certifications", "See", "also", "List", "number", "one", "hits", "2019", "Germany", "References"], "chinese_title": "Gladis Langzberry Hobby ", "chinese": ["Gladis", "Langzberry", "Hobby", "English", "Gladys", "Lounsbury", "Hobby", "November", "19", "1993", "born", "New", "York", "US", "microbiologist", "studies", "human", "counterbox", "The", "awareness", "drug", "research", "development", "played", "pivotal", "role", "During", "Second", "World", "War", "research", "results", "took", "penicillin", "test", "stage", "large", "scale", "production", "phase", "Reference", "material"]}