{"topic": "Driver Not Included", "english_title": "Driver Not Included", "english": ["Driver", "Not", "Included", "debut", "studio", "album", "American", "rock", "band", "Orange", "9mm", "It", "released", "1995", "Elektra", "Records", "Considered", "landmark", "release", "1990", "New", "York", "hardcore", "scene", "album", "incorporates", "influences", "funk", "heavy", "metal", "Critical", "reception", "AllMusic", "critic", "Jason", "Anderson", "described", "album", "strong", "effort", "stating", "This", "1995", "Elektra", "release", "deserves", "place", "among", "list", "important", "90s", "aggro", "punk", "hardcore", "releases", "Track", "listing", "All", "tracks", "written", "Orange", "9mm", "except", "noted", "Glistening", "2", "32", "High", "Speed", "Changer", "2", "53", "Disclaimer", "2", "34", "Suspect", "3", "57", "Pissed", "3", "04", "Toilet", "2", "19", "Magnet", "3", "09", "Guyatone", "3", "35", "Thickest", "Glass", "3", "02", "Can", "Decide", "3", "15", "Sacrifice", "4", "27", "Cutting", "Draining", "3", "27", "Personnel", "Adapted", "AllMusic", "Mike", "Bloom", "photography", "Bryan", "Carlstrom", "engineer", "Annette", "Cisneros", "assistant", "engineer", "Matthew", "Cross", "drums", "Matthew", "Curry", "assistant", "engineer", "Nick", "DiDia", "mixing", "Jim", "Evans", "art", "direction", "Don", "Fury", "mixing", "Dave", "Jerden", "mixing", "producer", "Chaka", "Malik", "vocals", "George", "Marino", "mastering", "Tim", "Owen", "photography", "Chris", "Traynor", "guitar", "Davide", "Gentile", "bass", "Charts", "References", "External", "links", "Driver", "Not", "Included", "Discogs", "list", "releases"], "chinese_title": "Comparison of file systems ", "chinese": ["The", "following", "table", "compares", "series", "file", "systems", "general", "technical", "information", "specific", "information", "file", "system", "used", "see", "link", "article", "General", "information", "limit", "metadata", "Features", "Allocation", "layout", "policies", "Supported", "operating", "system", "See", "Comparison", "Archive", "Formats", "Comparison", "File", "Archivers", "List", "archive", "formats", "List", "file", "archivers", "List", "file", "systems", "List", "default", "file", "systems", "List", "partition", "Types", "Comment", "External", "link", "A", "Speed", "Comparison", "Of", "FileSystems", "Linux", "2", "4", "5", "Archived", "FileSystems", "EXT3", "Reiser", "XFS", "JFS", "Comparison", "On", "Debian", "Etch", "April", "23", "2006"]}